previs/__init__.py
previs/core.py
previs/display.py
previs/instr.py
previs/sed.py
previs/utils.py
previs/_cli/__init__.py
previs/_cli/commands.py
previs/_cli/main.py
previs/data/eso_limits_matisse.json
previs/data/vizier_catalog_references.json
previs_astro-1.0.1.dist-info/LICENSE
previs_astro-1.0.1.dist-info/METADATA
previs_astro-1.0.1.dist-info/WHEEL
previs_astro-1.0.1.dist-info/entry_points.txt
previs_astro-1.0.1.dist-info/top_level.txt
previs_astro-1.0.1.dist-info/RECORD
