Metadata-Version: 2.1
Name: previs-astro
Version: 1.0.1
Author-email: Anthony Soulain <anthony.soulain@univ-grenoble-alpes.fr>
License: MIT
Project-URL: Homepage, https://github.com/DrSoulain/PREVIS
Classifier: Development Status :: 5 - Production/Stable
Classifier: Intended Audience :: Science/Research
Classifier: License :: OSI Approved :: MIT License
Classifier: Operating System :: MacOS :: MacOS X
Classifier: Operating System :: POSIX :: AIX
Classifier: Operating System :: POSIX :: Linux
Classifier: Programming Language :: Python :: 3
Classifier: Programming Language :: Python :: 3 :: Only
Classifier: Topic :: Scientific/Engineering :: Astronomy
Classifier: Typing :: Typed
Requires-Python: >=3.8
License-File: LICENSE
Requires-Dist: astropy
Requires-Dist: lxml
Requires-Dist: astroquery
Requires-Dist: matplotlib
Requires-Dist: scipy
Requires-Dist: emcee
Requires-Dist: pandas
Requires-Dist: numpy
Requires-Dist: termcolor
Requires-Dist: uncertainties
Requires-Dist: multiprocess
